plain/pageviews/CHANGELOG.md
plain/pageviews/README.md
plain/pageviews/__init__.py
plain/pageviews/admin.py
plain/pageviews/chores.py
plain/pageviews/config.py
plain/pageviews/default_settings.py
plain/pageviews/models.py
plain/pageviews/params.py
plain/pageviews/templates.py
plain/pageviews/urls.py
plain/pageviews/views.py
plain/pageviews/assets/pageviews/pageviews.js
plain/pageviews/migrations/0001_initial.py
plain/pageviews/migrations/0002_remove_pageview_plainpagevi_session_5545cf_idx_and_more.py
plain/pageviews/migrations/0003_pageview_campaign_pageview_medium_pageview_source_and_more.py
plain/pageviews/migrations/0004_remove_pageview_plainpageviews_pageview_unique_uuid_and_more.py
plain/pageviews/migrations/__init__.py
plain/pageviews/templates/pageviews/card.html
plain/pageviews/templates/pageviews/js.html
plain_pageviews-0.32.0.dist-info/METADATA
plain_pageviews-0.32.0.dist-info/WHEEL
plain_pageviews-0.32.0.dist-info/licenses/LICENSE
plain_pageviews-0.32.0.dist-info/RECORD
