Metadata-Version: 2.4
Name: plain.pageviews
Version: 0.32.0
Summary: Track pageviews from the client-side.
Author-email: Dave Gaeddert <dave.gaeddert@dropseed.dev>
License-Expression: BSD-3-Clause
License-File: LICENSE
Requires-Python: >=3.13
Requires-Dist: plain-models<1.0.0
Requires-Dist: plain<1.0.0
